{
  "date": "2013-01-10",
  "pdf": "http://wsdownload.bbc.co.uk/learningenglish/pdf/2013/01/130110170802_6min_pigeon_message.pdf",
  "description": "Can you crack the code?\n\nA message from the Second World War attached to the leg of a dead pigeon has proved difficult to understand.\nCallum and Neil learn more about secret codes and messenger birds.\nThis week's question:\nWho was the first person recorded to use written codes to keep his communications secret?\na: Julius Caesar\nb: King Harold\nc: Tutankhamun\nListen out for the answer at the end of the programme.\nOmnishambles\nEnd of Section\nShow All | Hide All\na common bird which can be trained to fly back to a particular place from wherever it is released\na brick structure in a house which takes smoke from a fireplace up and out of the house, usually through the roof\nto work out the meaning of a hidden message\na tool or technique for creating unbreakable codes\nunique, unpredictable, without any pattern\n",
  "words": [
    {
      "dt": "a pigeon",
      "dd": "a common bird which can be trained to fly back to a particular place from wherever it is released"
    },
    {
      "dt": "a chimney",
      "dd": "a brick structure in a house which takes smoke from a fireplace up and out of the house, usually through the roof"
    },
    {
      "dt": "to crack / break (a code)",
      "dd": "to work out the meaning of a hidden message"
    },
    {
      "dt": "a one-time pad",
      "dd": "a tool or technique for creating unbreakable codes"
    },
    {
      "dt": "random",
      "dd": "unique, unpredictable, without any pattern"
    }
  ],
  "title": "Messenger bird from the past",
  "audio": "http://http-ws.bbc.co.uk.edgesuite.net/mp3/learningenglish/2013/01/6min_messenger_bird_130110_6min_messenger_bird_audio_au_bb.mp3"
}